[
    {
        "ministry": "JABATAN PERDANA MENTERI (JPM)",
        "department": "AGENSI PENGURUSAN BENCANA NEGARA (NADMA)"
    },
    {
        "ministry": "JABATAN PERDANA MENTERI (JPM)",
        "department": "ANGKATAN PERTAHANAN AWAM MALAYSIA (APM)"
    },
    {
        "ministry": "JABATAN PERDANA MENTERI (JPM)",
        "department": "BAHAGIAN HAL EHWAL UNDANG-UNDANG (BHEUU)"
    },
    {
        "ministry": "JABATAN PERDANA MENTERI (JPM)",
        "department": "BAHAGIAN ISTIADAT DAN URUS SETIA PERSIDANGAN ANTARABANGSA (BIUPA)"
    },
    {
        "ministry": "JABATAN PERDANA MENTERI (JPM)",
        "department": "BAHAGIAN KABINET, PERLEMBAGAAN DAN PERHUBUNGAN ANTARA KERAJAAN (BKPP)"
    },
    {
        "ministry": "JABATAN PERDANA MENTERI (JPM)",
        "department": "BAHAGIAN PENGURUSAN HARTANAH"
    },
    {
        "ministry": "JABATAN PERDANA MENTERI (JPM)",
        "department": "BAHAGIAN PERLINDUNGAN"
    },
    {
        "ministry": "JABATAN PERDANA MENTERI (JPM)",
        "department": "INSTITUT LATIHAN KEHAKIMAN DAN PERUNDANGAN (ILKAP)"
    },
    {
        "ministry": "JABATAN PERDANA MENTERI (JPM)",
        "department": "INSTITUT TADBIRAN AWAM NEGARA (INTAN)"
    },
    {
        "ministry": "JABATAN PERDANA MENTERI (JPM)",
        "department": "ISTANA NEGARA"
    },
    {
        "ministry": "JABATAN PERDANA MENTERI (JPM)",
        "department": "JABATAN AGAMA ISLAM WILAYAH PERSEKUTUAN (JAWI)"
    },
    {
        "ministry": "JABATAN PERDANA MENTERI (JPM)",
        "department": "JABATAN AUDIT NEGARA"
    },
    {
        "ministry": "JABATAN PERDANA MENTERI (JPM)",
        "department": "JABATAN INSOLVENSI MALAYSIA"
    },
    {
        "ministry": "JABATAN PERDANA MENTERI (JPM)",
        "department": "JABATAN KEHAKIMAN SYARIAH MALAYSIA (JKSM)"
    },
    {
        "ministry": "JABATAN PERDANA MENTERI (JPM)",
        "department": "JABATAN KEMAJUAN ISLAM MALAYSIA (JAKIM)"
    },
    {
        "ministry": "JABATAN PERDANA MENTERI (JPM)",
        "department": "JABATAN KEMAJUAN ORANG ASLI (JAKOA)"
    },
    {
        "ministry": "JABATAN PERDANA MENTERI (JPM)",
        "department": "JABATAN PEGUAM NEGARA"
    },
    {
        "ministry": "JABATAN PERDANA MENTERI (JPM)",
        "department": "JABATAN PERDANA MENTERI"
    },
    {
        "ministry": "JABATAN PERDANA MENTERI (JPM)",
        "department": "JABATAN PERKHIDMATAN AWAM"
    },
    {
        "ministry": "JABATAN PERDANA MENTERI (JPM)",
        "department": "KHAZANAH NASIONAL BERHAD"
    },
    {
        "ministry": "JABATAN PERDANA MENTERI (JPM)",
        "department": "LEMBAGA PEMBANGUNAN LANGKAWI (LADA)"
    },
    {
        "ministry": "JABATAN PERDANA MENTERI (JPM)",
        "department": "LEMBAGA PENASIHAT"
    },
    {
        "ministry": "JABATAN PERDANA MENTERI (JPM)",
        "department": "LEMBAGA TABUNG HAJI"
    },
    {
        "ministry": "JABATAN PERDANA MENTERI (JPM)",
        "department": "LEMBAGA WAKAF HINDU NEGERI PULAU PINANG"
    },
    {
        "ministry": "JABATAN PERDANA MENTERI (JPM)",
        "department": "MAHKAMAH SYARIAH WILAYAH PERSEKUTUAN"
    },
    {
        "ministry": "JABATAN PERDANA MENTERI (JPM)",
        "department": "MAJLIS AGAMA ISLAM WILAYAH PERSEKUTUAN (MAIWP)"
    },
    {
        "ministry": "JABATAN PERDANA MENTERI (JPM)",
        "department": "MAJLIS KESELAMATAN NEGARA"
    },
    {
        "ministry": "JABATAN PERDANA MENTERI (JPM)",
        "department": "MALAYSIAN INDUSTRY-GROUP FOR HIGH TECHNOLOGY (MIGHT)"
    },
    {
        "ministry": "JABATAN PERDANA MENTERI (JPM)",
        "department": "PARLIMEN MALAYSIA"
    },
    {
        "ministry": "JABATAN PERDANA MENTERI (JPM)",
        "department": "PEJABAT KETUA PEGAWAI KESELAMATAN KERAJAAN MALAYSIA"
    },
    {
        "ministry": "JABATAN PERDANA MENTERI (JPM)",
        "department": "PEJABAT KETUA PENDAFTAR MAHKAMAH PERSEKUTUAN MALAYSIA"
    },
    {
        "ministry": "JABATAN PERDANA MENTERI (JPM)",
        "department": "PEJABAT MUFTI WILAYAH PERSEKUTUAN"
    },
    {
        "ministry": "JABATAN PERDANA MENTERI (JPM)",
        "department": "PEJABAT PENYIMPAN MOHOR BESAR RAJA-RAJA MALAYSIA"
    },
    {
        "ministry": "JABATAN PERDANA MENTERI (JPM)",
        "department": "PERBADANAN USAHAWAN NASIONAL BERHAD (PUNB)"
    },
    {
        "ministry": "JABATAN PERDANA MENTERI (JPM)",
        "department": "PERMODALAN NASIONAL BERHAD (PNB)"
    },
    {
        "ministry": "JABATAN PERDANA MENTERI (JPM)",
        "department": "PETROLIAM NASIONAL BERHAD (PETRONAS)"
    },
    {
        "ministry": "JABATAN PERDANA MENTERI (JPM)",
        "department": "PUSAT GOVERNANS, INTEGRITI DAN ANTI-RASUAH NASIONAL (GIACC)"
    },
    {
        "ministry": "JABATAN PERDANA MENTERI (JPM)",
        "department": "PUSAT TIMBANG TARA SERANTAU ASIA (AIAC)"
    },
    {
        "ministry": "JABATAN PERDANA MENTERI (JPM)",
        "department": "SURUHANJAYA HAK ASASI MANUSIA (SUHAKAM)"
    },
    {
        "ministry": "JABATAN PERDANA MENTERI (JPM)",
        "department": "SURUHANJAYA INTEGRITI AGENSI PENGUATKUASAAN (EAIC) "
    },
    {
        "ministry": "JABATAN PERDANA MENTERI (JPM)",
        "department": "SURUHANJAYA PENCEGAHAN RASUAH MALAYSIA (SPRM)"
    },
    {
        "ministry": "JABATAN PERDANA MENTERI (JPM)",
        "department": "SURUHANJAYA PERKHIDMATAN AWAM MALAYSIA (SPA)"
    },
    {
        "ministry": "JABATAN PERDANA MENTERI (JPM)",
        "department": "SURUHANJAYA PERKHIDMATAN KEHAKIMAN DAN PERUNDANGAN"
    },
    {
        "ministry": "JABATAN PERDANA MENTERI (JPM)",
        "department": "SURUHANJAYA PERKHIDMATAN PELAJARAN (SPP)"
    },
    {
        "ministry": "JABATAN PERDANA MENTERI (JPM)",
        "department": "SURUHANJAYA PILIHAN RAYA MALAYSIA"
    },
    {
        "ministry": "JABATAN PERDANA MENTERI (JPM)",
        "department": "UNIT PEMODENAN TADBIRAN DAN PERANCANGAN PENGURUSAN MALAYSIA (MAMPU)"
    },
    {
        "ministry": "JABATAN PERDANA MENTERI (JPM)",
        "department": "UNIT PENYELARASAN PELAKSANAAN (ICU)"
    },
    {
        "ministry": "JABATAN PERDANA MENTERI (JPM)",
        "department": "UNIT PERANCANG EKONOMI (EPU)"
    },
    {
        "ministry": "JABATAN PERDANA MENTERI (JPM)",
        "department": "UNIT TRANSFORMASI MASYARAKAT INDIA MALAYSIA (MITRA)"
    },
    {
        "ministry": "JABATAN PERDANA MENTERI (JPM)",
        "department": "URUSETIA JAWATANKUASA KERJA TANAH WILAYAH PERSEKUTUAN"
    },
    {
        "ministry": "KEMENTERIAN BELIA DAN SUKAN",
        "department": "INSTITUT KEMAHIRAN BELIA NEGARA (IKBN) ALOR GAJAH"
    },
    {
        "ministry": "KEMENTERIAN BELIA DAN SUKAN",
        "department": "INSTITUT PENYELIDIKAN PEMBANGUNAN BELIA MALAYSIA (IYRES)"
    },
    {
        "ministry": "KEMENTERIAN BELIA DAN SUKAN",
        "department": "INSTITUT SUKAN NEGARA(ISN)"
    },
    {
        "ministry": "KEMENTERIAN BELIA DAN SUKAN",
        "department": "JABATAN BELIA DAN SUKAN NEGARA"
    },
    {
        "ministry": "KEMENTERIAN BELIA DAN SUKAN",
        "department": "KEMENTERIAN BELIA DAN SUKAN"
    },
    {
        "ministry": "KEMENTERIAN BELIA DAN SUKAN",
        "department": "MAJLIS SUKAN NEGARA(MSN)"
    },
    {
        "ministry": "KEMENTERIAN BELIA DAN SUKAN",
        "department": "PEJABAT PENDAFTAR PERTUBUHAN BELIA"
    },
    {
        "ministry": "KEMENTERIAN BELIA DAN SUKAN",
        "department": "PEJABAT PESURUHJAYA SUKAN"
    },
    {
        "ministry": "KEMENTERIAN BELIA DAN SUKAN",
        "department": "PERBADANAN STADIUM MALAYSIA"
    },
    {
        "ministry": "KEMENTERIAN DALAM NEGERI",
        "department": "AGENSI ANTIDADAH KEBANGSAAN (AADK)"
    },
    {
        "ministry": "KEMENTERIAN DALAM NEGERI",
        "department": "AGENSI KAWALAN SEMPADAN MALAYSIA (AKSEM)"
    },
    {
        "ministry": "KEMENTERIAN DALAM NEGERI",
        "department": "AGENSI PENGUATKUASAAN MARITIM MALAYSIA (APMM)"
    },
    {
        "ministry": "KEMENTERIAN DALAM NEGERI",
        "department": "INSTITUT KESELAMATAN AWAM MALAYSIA (IPSOM)"
    },
    {
        "ministry": "KEMENTERIAN DALAM NEGERI",
        "department": "JABATAN IMIGRESEN MALAYSIA"
    },
    {
        "ministry": "KEMENTERIAN DALAM NEGERI",
        "department": "JABATAN PENDAFTARAN NEGARA (JPN)"
    },
    {
        "ministry": "KEMENTERIAN DALAM NEGERI",
        "department": "JABATAN PENDAFTARAN PERTUBUHAN MALAYSIA (JPPM)"
    },
    {
        "ministry": "KEMENTERIAN DALAM NEGERI",
        "department": "JABATAN PENJARA MALAYSIA"
    },
    {
        "ministry": "KEMENTERIAN DALAM NEGERI",
        "department": "JABATAN SUKARELAWAN MALAYSIA (RELA)"
    },
    {
        "ministry": "KEMENTERIAN DALAM NEGERI",
        "department": "KAWASAN KESELAMATAN KHAS PANTAI TIMUR SABAH (ESSCOM)"
    },
    {
        "ministry": "KEMENTERIAN DALAM NEGERI",
        "department": "LEMBAGA PENAPIS FILEM"
    },
    {
        "ministry": "KEMENTERIAN DALAM NEGERI",
        "department": "POLIS DIRAJA MALAYSIA (PDRM)"
    },
    {
        "ministry": "KEMENTERIAN HAL EHWAL EKONOMI",
        "department": "JABATAN PERANGKAAN MALAYSIA"
    },
    {
        "ministry": "KEMENTERIAN HAL EHWAL EKONOMI",
        "department": "KEMENTERIAN HAL EHWAL EKONOMI"
    },
    {
        "ministry": "KEMENTERIAN HAL EHWAL EKONOMI",
        "department": "PERBADANAN KEMAJUAN IKTISAD NEGERI KELANTAN"
    },
    {
        "ministry": "KEMENTERIAN HAL EHWAL EKONOMI",
        "department": "PERBADANAN KEMAJUAN NEGERI PERAK"
    },
    {
        "ministry": "KEMENTERIAN HAL EHWAL EKONOMI",
        "department": "PERBADANAN KEMAJUAN NEGERI SELANGOR"
    },
    {
        "ministry": "KEMENTERIAN HAL EHWAL EKONOMI",
        "department": "PERBADANAN SUMBER PETROLEUM MALAYSIA"
    },
    {
        "ministry": "KEMENTERIAN HAL EHWAL EKONOMI",
        "department": "PIHAK BERKUASA KEMAJUAN PEKEBUN KECIL PERUSAHAAN GETAH"
    },
    {
        "ministry": "KEMENTERIAN HAL EHWAL EKONOMI",
        "department": "UNIT PENERAJU AGENDA BUMIPUTERA (TERAJU)"
    },
    {
        "ministry": "KEMENTERIAN HAL EHWAL EKONOMI",
        "department": "YAYASAN AMANAH HARTANAH BUMIPUTERA (YAHB)"
    },
    {
        "ministry": "KEMENTERIAN INDUSTRI UTAMA",
        "department": "INSTITUT PERLADANGAN DAN KOMODITI MALAYSIA"
    },
    {
        "ministry": "KEMENTERIAN INDUSTRI UTAMA",
        "department": "KEMENTERIAN INDUSTRI UTAMA"
    },
    {
        "ministry": "KEMENTERIAN INDUSTRI UTAMA",
        "department": "LEMBAGA GETAH MALAYSIA"
    },
    {
        "ministry": "KEMENTERIAN INDUSTRI UTAMA",
        "department": "LEMBAGA KENAF DAN TEMBAKAU NEGARA (LKTN)"
    },
    {
        "ministry": "KEMENTERIAN INDUSTRI UTAMA",
        "department": "LEMBAGA KOKO MALAYSIA"
    },
    {
        "ministry": "KEMENTERIAN INDUSTRI UTAMA",
        "department": "LEMBAGA LADA MALAYSIA (MPB)"
    },
    {
        "ministry": "KEMENTERIAN INDUSTRI UTAMA",
        "department": "LEMBAGA MINYAK SAWIT MALAYSIA (MPOB)"
    },
    {
        "ministry": "KEMENTERIAN INDUSTRI UTAMA",
        "department": "LEMBAGA PERINDUSTRIAN KAYU MALAYSIA"
    },
    {
        "ministry": "KEMENTERIAN INDUSTRI UTAMA",
        "department": "MAJLIS KAYU KAYAN MALAYSIA"
    },
    {
        "ministry": "KEMENTERIAN INDUSTRI UTAMA",
        "department": "MAJLIS MINYAK SAWIT MALAYSIA (MPOC)"
    },
    {
        "ministry": "KEMENTERIAN INDUSTRI UTAMA",
        "department": "MAJLIS PENSIJILAN KAYU MALAYSIA"
    },
    {
        "ministry": "KEMENTERIAN INDUSTRI UTAMA",
        "department": "MAJLIS PENSIJILAN MINYAK SAWIT MALAYSIA (MPOCC)"
    },
    {
        "ministry": "KEMENTERIAN INDUSTRI UTAMA",
        "department": "MAJLIS PROMOSI EKSPORT GETAH MALAYSIA"
    },
    {
        "ministry": "KEMENTERIAN KERJA RAYA (KKR)",
        "department": "JABATAN KERJA RAYA"
    },
    {
        "ministry": "KEMENTERIAN KERJA RAYA (KKR)",
        "department": "KEMENTERIAN KERJA RAYA"
    },
    {
        "ministry": "KEMENTERIAN KERJA RAYA (KKR)",
        "department": "LEMBAGA ARKITEK MALAYSIA"
    },
    {
        "ministry": "KEMENTERIAN KERJA RAYA (KKR)",
        "department": "LEMBAGA JURUTERA MALAYSIA"
    },
    {
        "ministry": "KEMENTERIAN KERJA RAYA (KKR)",
        "department": "LEMBAGA JURUUKUR BAHAN MALAYSIA"
    },
    {
        "ministry": "KEMENTERIAN KERJA RAYA (KKR)",
        "department": "LEMBAGA LEBUHRAYA MALAYSIA"
    },
    {
        "ministry": "KEMENTERIAN KERJA RAYA (KKR)",
        "department": "LEMBAGA PEMBANGUNAN INDUSTRI PEMBINAAN (CIDB)"
    },
    {
        "ministry": "KEMENTERIAN KESIHATAN MALAYSIA",
        "department": "INSTITUT KANSER NEGARA"
    },
    {
        "ministry": "KEMENTERIAN KESIHATAN MALAYSIA",
        "department": "INSTITUT KESIHATAN NEGARA"
    },
    {
        "ministry": "KEMENTERIAN KESIHATAN MALAYSIA",
        "department": "INSTITUT KESIHATAN UMUM"
    },
    {
        "ministry": "KEMENTERIAN KESIHATAN MALAYSIA",
        "department": "INSTITUT PENGURUSAN KESIHATAN"
    },
    {
        "ministry": "KEMENTERIAN KESIHATAN MALAYSIA",
        "department": "INSTITUT PENYELIDIKAN PERUBATAN"
    },
    {
        "ministry": "KEMENTERIAN KESIHATAN MALAYSIA",
        "department": "INSTITUT PENYELIDIKAN SISTEM KESIHATAN"
    },
    {
        "ministry": "KEMENTERIAN KESIHATAN MALAYSIA",
        "department": "INSTITUT PENYELIDIKAN TINGKAHLAKU KESIHATAN"
    },
    {
        "ministry": "KEMENTERIAN KESIHATAN MALAYSIA",
        "department": "INSTITUT PERUBATAN RESPIRATORI"
    },
    {
        "ministry": "KEMENTERIAN KESIHATAN MALAYSIA",
        "department": "KEMENTERIAN KESIHATAN"
    },
    {
        "ministry": "KEMENTERIAN KESIHATAN MALAYSIA",
        "department": "MALAYSIA HEALTHCARE TRAVEL COUNCIL (MHTC)"
    },
    {
        "ministry": "KEMENTERIAN KESIHATAN MALAYSIA",
        "department": "PIHAK BERKUASA PERANTI PERUBATAN (PBPP)"
    },
    {
        "ministry": "KEMENTERIAN KESIHATAN MALAYSIA",
        "department": "PUSAT DARAH NEGARA"
    },
    {
        "ministry": "KEMENTERIAN KESIHATAN MALAYSIA",
        "department": "PUSAT KAWALAN KUSTA NEGARA"
    },
    {
        "ministry": "KEMENTERIAN KESIHATAN MALAYSIA",
        "department": "PUSAT PERGIGIAN KANAK-KANAK & KOLEJ LATIHAN PERGIGIAN MALAYSIA"
    },
    {
        "ministry": "KEMENTERIAN KEWANGAN",
        "department": "AGENSI KAUNSELING DAN PENGURUSAN KREDIT (AKPK)"
    },
    {
        "ministry": "KEMENTERIAN KEWANGAN",
        "department": "BANK NEGARA MALAYSIA (BNM)"
    },
    {
        "ministry": "KEMENTERIAN KEWANGAN",
        "department": "BANK SIMPANAN NASIONAL (BSN)"
    },
    {
        "ministry": "KEMENTERIAN KEWANGAN",
        "department": "BURSA MALAYSIA BERHAD"
    },
    {
        "ministry": "KEMENTERIAN KEWANGAN",
        "department": "JABATAN AKAUNTAN NEGARA MALAYSIA (JANM)"
    },
    {
        "ministry": "KEMENTERIAN KEWANGAN",
        "department": "JABATAN KASTAM DIRAJA MALAYSIA (JKDM)"
    },
    {
        "ministry": "KEMENTERIAN KEWANGAN",
        "department": "JABATAN PENILAIAN DAN PERKHIDMATAN HARTA (JPPH)"
    },
    {
        "ministry": "KEMENTERIAN KEWANGAN",
        "department": "KEMENTERIAN KEWANGAN"
    },
    {
        "ministry": "KEMENTERIAN KEWANGAN",
        "department": "KUMPULAN WANG PERSARAAN (DIPERBADANKAN) (KWAP) - PERKHIDMATAN PERSARAAN"
    },
    {
        "ministry": "KEMENTERIAN KEWANGAN",
        "department": "KUMPULAN WANG SIMPANAN PEKERJA (KWSP)"
    },
    {
        "ministry": "KEMENTERIAN KEWANGAN",
        "department": "LEMBAGA HASIL DALAM NEGERI MALAYSIA(LHDNM)"
    },
    {
        "ministry": "KEMENTERIAN KEWANGAN",
        "department": "LEMBAGA PEMBIAYAAN PERUMAHAN SEKTOR AWAM (LPPSA)"
    },
    {
        "ministry": "KEMENTERIAN KEWANGAN",
        "department": "LEMBAGA PERKHIDMATAN KEWANGAN LABUAN (LABUAN FSA)"
    },
    {
        "ministry": "KEMENTERIAN KEWANGAN",
        "department": "PERBADANAN MEMAJUKAN IKTISAD NEGERI TERENGGANU"
    },
    {
        "ministry": "KEMENTERIAN KEWANGAN",
        "department": "PERBENDAHARAAN SABAH"
    },
    {
        "ministry": "KEMENTERIAN KEWANGAN",
        "department": "PERBENDAHARAAN SARAWAK"
    },
    {
        "ministry": "KEMENTERIAN KEWANGAN",
        "department": "SURUHANJAYA SEKURITI"
    },
    {
        "ministry": "KEMENTERIAN KEWANGAN",
        "department": "UNIT KERJASAMA AWAM SWASTA (UKAS)"
    },
    {
        "ministry": "KEMENTERIAN KEWANGAN",
        "department": "YAYASAN TUN RAZAK "
    },
    {
        "ministry": "KEMENTERIAN KOMUNIKASI DAN MULTIMEDIA",
        "department": "CYBERSECURITY MALAYSIA"
    },
    {
        "ministry": "KEMENTERIAN KOMUNIKASI DAN MULTIMEDIA",
        "department": "INSTITUT PENYIARAN DAN PENERANGAN TUN ABDUL RAZAK (IPPTAR)"
    },
    {
        "ministry": "KEMENTERIAN KOMUNIKASI DAN MULTIMEDIA",
        "department": "JABATAN PENERANGAN MALAYSIA"
    },
    {
        "ministry": "KEMENTERIAN KOMUNIKASI DAN MULTIMEDIA",
        "department": "JABATAN PERLINDUNGAN DATA PERIBADI (JPDP)"
    },
    {
        "ministry": "KEMENTERIAN KOMUNIKASI DAN MULTIMEDIA",
        "department": "KEMENTERIAN KOMUNIKASI DAN MULTIMEDIA MALAYSIA"
    },
    {
        "ministry": "KEMENTERIAN KOMUNIKASI DAN MULTIMEDIA",
        "department": "MALAYSIA DIGITAL ECONOMY CORPORATION (MDEC)"
    },
    {
        "ministry": "KEMENTERIAN KOMUNIKASI DAN MULTIMEDIA",
        "department": "PERBADANAN KEMAJUAN FILEM NASIONAL MALAYSIA (FINAS)"
    },
    {
        "ministry": "KEMENTERIAN KOMUNIKASI DAN MULTIMEDIA",
        "department": "SURUHANJAYA KOMUNIKASI DAN MULTIMEDIA MALAYSIA (SKMM)"
    },
    {
        "ministry": "KEMENTERIAN LUAR NEGERI",
        "department": "INSTITUT DIPLOMASI DAN HUBUNGAN LUAR NEGERI (IDFR)"
    },
    {
        "ministry": "KEMENTERIAN LUAR NEGERI",
        "department": "KEMENTERIAN LUAR NEGERI"
    },
    {
        "ministry": "KEMENTERIAN LUAR NEGERI",
        "department": "PIHAK BERKUASA KEBANGSAAN KONVENSYEN SENJATA KIMIA"
    },
    {
        "ministry": "KEMENTERIAN LUAR NEGERI",
        "department": "PUSAT SERANTAU ASIA TENGGARA BAGI MENCEGAH KEGANASAN (SEARCCT)"
    },
    {
        "ministry": "KEMENTERIAN PELANCONGAN, SENI DAN BUDAYA MALAYSIA (MOTAC)",
        "department": "AKADEMI SENI BUDAYA DAN WARISAN KEBANGSAAN (ASWARA)"
    },
    {
        "ministry": "KEMENTERIAN PELANCONGAN, SENI DAN BUDAYA MALAYSIA (MOTAC)",
        "department": "ARKIB NEGARA MALAYSIA"
    },
    {
        "ministry": "KEMENTERIAN PELANCONGAN, SENI DAN BUDAYA MALAYSIA (MOTAC)",
        "department": "ISTANA BUDAYA"
    },
    {
        "ministry": "KEMENTERIAN PELANCONGAN, SENI DAN BUDAYA MALAYSIA (MOTAC)",
        "department": "JABATAN KEBUDAYAAN DAN KESENIAN NEGARA"
    },
    {
        "ministry": "KEMENTERIAN PELANCONGAN, SENI DAN BUDAYA MALAYSIA (MOTAC)",
        "department": "JABATAN MUZIUM MALAYSIA"
    },
    {
        "ministry": "KEMENTERIAN PELANCONGAN, SENI DAN BUDAYA MALAYSIA (MOTAC)",
        "department": "JABATAN WARISAN NEGARA"
    },
    {
        "ministry": "KEMENTERIAN PELANCONGAN, SENI DAN BUDAYA MALAYSIA (MOTAC)",
        "department": "KEMENTERIAN PELANCONGAN, SENI DAN BUDAYA MALAYSIA (MOTAC)"
    },
    {
        "ministry": "KEMENTERIAN PELANCONGAN, SENI DAN BUDAYA MALAYSIA (MOTAC)",
        "department": "LEMBAGA PEMBANGUNAN SENI VISUAL NEGARA"
    },
    {
        "ministry": "KEMENTERIAN PELANCONGAN, SENI DAN BUDAYA MALAYSIA (MOTAC)",
        "department": "LEMBAGA PENGGALAKAN PELANCONGAN MALAYSIA"
    },
    {
        "ministry": "KEMENTERIAN PELANCONGAN, SENI DAN BUDAYA MALAYSIA (MOTAC)",
        "department": "MALAYSIA CONVENTION & EXHIBITION BUREAU (MYCEB)"
    },
    {
        "ministry": "KEMENTERIAN PELANCONGAN, SENI DAN BUDAYA MALAYSIA (MOTAC)",
        "department": "PERBADANAN KEMAJUAN KRAFTANGAN MALAYSIA"
    },
    {
        "ministry": "KEMENTERIAN PELANCONGAN, SENI DAN BUDAYA MALAYSIA (MOTAC)",
        "department": "PERPUSTAKAAN NEGARA MALAYSIA"
    },
    {
        "ministry": "KEMENTERIAN PELANCONGAN, SENI DAN BUDAYA MALAYSIA (MOTAC)",
        "department": "PUSAT PELANCONGAN ISLAM"
    },
    {
        "ministry": "KEMENTERIAN PEMBANGUNAN LUAR BANDAR",
        "department": "LEMBAGA KEMAJUAN WILAYAH KEDAH (KEDA) "
    },
    {
        "ministry": "KEMENTERIAN PEMBANGUNAN LUAR BANDAR",
        "department": "MAJLIS AMANAH RAKYAT (MARA)"
    },
    {
        "ministry": "KEMENTERIAN PEMBANGUNAN LUAR BANDAR",
        "department": "MINISTRY OF RURAL DEVELOPMENT"
    },
    {
        "ministry": "KEMENTERIAN PEMBANGUNAN USAHAWAN DAN KOPERASI (MEDAC)",
        "department": "BANK RAKYAT"
    },
    {
        "ministry": "KEMENTERIAN PEMBANGUNAN USAHAWAN DAN KOPERASI (MEDAC)",
        "department": "INSTITUT KEUSAHAWAN NEGARA (INSKEN)"
    },
    {
        "ministry": "KEMENTERIAN PEMBANGUNAN USAHAWAN DAN KOPERASI (MEDAC)",
        "department": "INSTITUT KOPERASI MALAYSIA"
    },
    {
        "ministry": "KEMENTERIAN PEMBANGUNAN USAHAWAN DAN KOPERASI (MEDAC)",
        "department": "KEMENTERIAN PEMBANGUNAN USAHAWAN"
    },
    {
        "ministry": "KEMENTERIAN PEMBANGUNAN USAHAWAN DAN KOPERASI (MEDAC)",
        "department": "PERBADANAN NASIONAL BERHAD (PNS)"
    },
    {
        "ministry": "KEMENTERIAN PEMBANGUNAN USAHAWAN DAN KOPERASI (MEDAC)",
        "department": "PERBADANAN PERUSAHAAN KECIL DAN SEDERHANA MALAYSIA (SME CORP. MALAYSIA)"
    },
    {
        "ministry": "KEMENTERIAN PEMBANGUNAN USAHAWAN DAN KOPERASI (MEDAC)",
        "department": "PROTÉGÉ"
    },
    {
        "ministry": "KEMENTERIAN PEMBANGUNAN USAHAWAN DAN KOPERASI (MEDAC)",
        "department": "PUSAT INOVASI DAN KREATIVITI GLOBAL (MAGIC)"
    },
    {
        "ministry": "KEMENTERIAN PEMBANGUNAN USAHAWAN DAN KOPERASI (MEDAC)",
        "department": "SME BANK"
    },
    {
        "ministry": "KEMENTERIAN PEMBANGUNAN USAHAWAN DAN KOPERASI (MEDAC)",
        "department": "SURUHANJAYA KOPERASI MALAYSIA"
    },
    {
        "ministry": "KEMENTERIAN PEMBANGUNAN USAHAWAN DAN KOPERASI (MEDAC)",
        "department": "TEKUN NASIONAL"
    },
    {
        "ministry": "KEMENTERIAN PEMBANGUNAN USAHAWAN DAN KOPERASI (MEDAC)",
        "department": "UDA HOLDINGS BERHAD"
    },
    {
        "ministry": "KEMENTERIAN PEMBANGUNAN WANITA, KELUARGA DAN MASYARAKAT (KPWKM)",
        "department": "INSTITUT PENGUPAYAAN WANITA BAGI ANGGOTA PERGERAKAN NEGARA-NEGARA BERKECUALI (NAM), (NIEW)"
    },
    {
        "ministry": "KEMENTERIAN PEMBANGUNAN WANITA, KELUARGA DAN MASYARAKAT (KPWKM)",
        "department": "INSTITUT SOSIAL MALAYSIA (ISM)"
    },
    {
        "ministry": "KEMENTERIAN PEMBANGUNAN WANITA, KELUARGA DAN MASYARAKAT (KPWKM)",
        "department": "JABATAN KEBAJIKAN MASYARAKAT (JKM)"
    },
    {
        "ministry": "KEMENTERIAN PEMBANGUNAN WANITA, KELUARGA DAN MASYARAKAT (KPWKM)",
        "department": "JABATAN PEMBANGUNAN WANITA"
    },
    {
        "ministry": "KEMENTERIAN PEMBANGUNAN WANITA, KELUARGA DAN MASYARAKAT (KPWKM)",
        "department": "KEMENTERIAN PEMBANGUNAN WANITA, KELUARGA DAN MASYARAKAT"
    },
    {
        "ministry": "KEMENTERIAN PEMBANGUNAN WANITA, KELUARGA DAN MASYARAKAT (KPWKM)",
        "department": "LEMBAGA PENDUDUK DAN PEMBANGUNAN KELUARGA NEGARA (LPPKN)"
    },
    {
        "ministry": "KEMENTERIAN PENDIDIKAN",
        "department": "AGENSI KELAYAKAN MALAYSIA (MQA)"
    },
    {
        "ministry": "KEMENTERIAN PENDIDIKAN",
        "department": "AKADEMI KEPIMPINAN PENDIDIKAN TINGGI (AKEPT)"
    },
    {
        "ministry": "KEMENTERIAN PENDIDIKAN",
        "department": "DEWAN BAHASA DAN PUSTAKA (DBP)"
    },
    {
        "ministry": "KEMENTERIAN PENDIDIKAN",
        "department": "INSTITUT TERJEMAHAN & BUKU MALAYSIA"
    },
    {
        "ministry": "KEMENTERIAN PENDIDIKAN",
        "department": "JABATAN PENDIDIKAN POLITEKNIK & KOLEJ KOMUNITI"
    },
    {
        "ministry": "KEMENTERIAN PENDIDIKAN",
        "department": "JABATAN PENDIDIKAN TINGGI"
    },
    {
        "ministry": "KEMENTERIAN PENDIDIKAN",
        "department": "KEMENTERIAN PENDIDIKAN MALAYSIA"
    },
    {
        "ministry": "KEMENTERIAN PENDIDIKAN",
        "department": "MAJLIS PEPERIKSAAN MALAYSIA"
    },
    {
        "ministry": "KEMENTERIAN PENDIDIKAN",
        "department": "PERBADANAN KOTA BUKU (PKB)"
    },
    {
        "ministry": "KEMENTERIAN PENDIDIKAN",
        "department": "PERBADANAN TABUNG PENDIDIKAN TINGGI NASIONAL, (PTPTN)"
    },
    {
        "ministry": "KEMENTERIAN PENDIDIKAN",
        "department": "PERKHIDMATAN GLOBAL PENDIDIKAN MALAYSIA (EMGS)"
    },
    {
        "ministry": "KEMENTERIAN PENDIDIKAN",
        "department": "UNIT PELAKSANAAN DAN PRESTASI PENDIDIKAN (PADU)"
    },
    {
        "ministry": "KEMENTERIAN PENDIDIKAN",
        "department": "UNIVERSITI MALAYA (UM)"
    },
    {
        "ministry": "KEMENTERIAN PENDIDIKAN",
        "department": "UNIVERSITI MALAYSIA PERLIS (UNIMAP)"
    },
    {
        "ministry": "KEMENTERIAN PENDIDIKAN",
        "department": "UNIVERSITI MALAYSIA SARAWAK (UNIMAS)"
    },
    {
        "ministry": "KEMENTERIAN PENDIDIKAN",
        "department": "UNIVERSITI PENDIDIKAN SULTAN IDRIS (UPSI)"
    },
    {
        "ministry": "KEMENTERIAN PENDIDIKAN",
        "department": "UNIVERSITI PERTAHANAN NASIONAL MALAYSIA (UPNM)"
    },
    {
        "ministry": "KEMENTERIAN PENDIDIKAN",
        "department": "UNIVERSITI PUTRA MALAYSIA (UPM)"
    },
    {
        "ministry": "KEMENTERIAN PENDIDIKAN",
        "department": "UNIVERSITI SAINS MALAYSIA (USM)"
    },
    {
        "ministry": "KEMENTERIAN PENDIDIKAN",
        "department": "UNIVERSITI TEKNIKAL MALAYSIA MELAKA (UTEM)"
    },
    {
        "ministry": "KEMENTERIAN PENDIDIKAN",
        "department": "UNIVERSITI TEKNOLOGI MARA (UITM)"
    },
    {
        "ministry": "KEMENTERIAN PENDIDIKAN",
        "department": "UNIVERSITI UTARA MALAYSIA (UUM)"
    },
    {
        "ministry": "KEMENTERIAN PENGANGKUTAN",
        "department": "AGENSI PENGANGKUTAN AWAM DARAT (APAD)"
    },
    {
        "ministry": "KEMENTERIAN PENGANGKUTAN",
        "department": "INSTITUT MARITIM MALAYSIA (MIMA)"
    },
    {
        "ministry": "KEMENTERIAN PENGANGKUTAN",
        "department": "INSTITUT PENYELIDIKAN KESELAMATAN JALAN RAYA (MIROS)"
    },
    {
        "ministry": "KEMENTERIAN PENGANGKUTAN",
        "department": "JABATAN KESELAMATAN JALAN RAYA (JKJR)"
    },
    {
        "ministry": "KEMENTERIAN PENGANGKUTAN",
        "department": "JABATAN LAUT MALAYSIA"
    },
    {
        "ministry": "KEMENTERIAN PENGANGKUTAN",
        "department": "JABATAN PENGANGKUTAN JALAN (JPJ)"
    },
    {
        "ministry": "KEMENTERIAN PENGANGKUTAN",
        "department": "KEMENTERIAN PENGANGKUTAN MALAYSIA"
    },
    {
        "ministry": "KEMENTERIAN PENGANGKUTAN",
        "department": "LEMBAGA PELABUHAN BINTULU"
    },
    {
        "ministry": "KEMENTERIAN PENGANGKUTAN",
        "department": "LEMBAGA PELABUHAN JOHOR"
    },
    {
        "ministry": "KEMENTERIAN PENGANGKUTAN",
        "department": "LEMBAGA PELABUHAN KELANG"
    },
    {
        "ministry": "KEMENTERIAN PENGANGKUTAN",
        "department": "LEMBAGA PELABUHAN KUANTAN"
    },
    {
        "ministry": "KEMENTERIAN PENGANGKUTAN",
        "department": "LEMBAGA PELESENAN KENDERAAN PERDAGANGAN SABAH"
    },
    {
        "ministry": "KEMENTERIAN PENGANGKUTAN",
        "department": "LEMBAGA PELESENAN KENDERAAN PERDAGANGAN SARAWAK"
    },
    {
        "ministry": "KEMENTERIAN PENGANGKUTAN",
        "department": "PERBADANAN ASET KERETAPI"
    },
    {
        "ministry": "KEMENTERIAN PENGANGKUTAN",
        "department": "PIHAK BERKUASA PENERBANGAN AWAM MALAYSIA (CAAM)"
    },
    {
        "ministry": "KEMENTERIAN PENGANGKUTAN",
        "department": "PRASARANA MALAYSIA BERHAD "
    },
    {
        "ministry": "KEMENTERIAN PENGANGKUTAN",
        "department": "SURUHANJAYA PELABUHAN PULAU PINANG"
    },
    {
        "ministry": "KEMENTERIAN PERDAGANGAN ANTARABANGSA DAN INDUSTRI",
        "department": "EXPORT-IMPORT BANK OF MALAYSIA BERHAD (EXIM BANK)"
    },
    {
        "ministry": "KEMENTERIAN PERDAGANGAN ANTARABANGSA DAN INDUSTRI",
        "department": "INSTITUT AUTOMOTIF ROBOTIK DAN IOT MALAYSIA (MARII)"
    },
    {
        "ministry": "KEMENTERIAN PERDAGANGAN ANTARABANGSA DAN INDUSTRI",
        "department": "INVESTKL MALAYSIA"
    },
    {
        "ministry": "KEMENTERIAN PERDAGANGAN ANTARABANGSA DAN INDUSTRI",
        "department": "JABATAN STANDARD MALAYSIA (JSM)"
    },
    {
        "ministry": "KEMENTERIAN PERDAGANGAN ANTARABANGSA DAN INDUSTRI",
        "department": "KEMENTERIAN PERDAGANGAN ANTARABANGSA DAN INDUSTRI (MITI)"
    },
    {
        "ministry": "KEMENTERIAN PERDAGANGAN ANTARABANGSA DAN INDUSTRI",
        "department": "LEMBAGA PEMBANGUNAN PELABURAN MALAYSIA (MIDA)"
    },
    {
        "ministry": "KEMENTERIAN PERDAGANGAN ANTARABANGSA DAN INDUSTRI",
        "department": "MALAYSIAN INDUSTRIAL DEVELOPMENT FINANCE (MIDF)"
    },
    {
        "ministry": "KEMENTERIAN PERDAGANGAN ANTARABANGSA DAN INDUSTRI",
        "department": "MALAYSIA STEEL INSTITUTE (MSI)"
    },
    {
        "ministry": "KEMENTERIAN PERDAGANGAN ANTARABANGSA DAN INDUSTRI",
        "department": "MIMOS BERHAD"
    },
    {
        "ministry": "KEMENTERIAN PERDAGANGAN ANTARABANGSA DAN INDUSTRI",
        "department": "PERBADANAN PEMBANGUNAN INDUSTRI KECIL DAN SEDERHANA (SME. CORP MALAYSIA)"
    },
    {
        "ministry": "KEMENTERIAN PERDAGANGAN ANTARABANGSA DAN INDUSTRI",
        "department": "PERBADANAN PEMBANGUNAN PERDAGANGAN LUAR MALAYSIA (MATRADE)"
    },
    {
        "ministry": "KEMENTERIAN PERDAGANGAN ANTARABANGSA DAN INDUSTRI",
        "department": "PERBADANAN PRODUKTIVITI MALAYSIA (MPC)"
    },
    {
        "ministry": "KEMENTERIAN PERDAGANGAN ANTARABANGSA DAN INDUSTRI",
        "department": "SIRIM BERHAD"
    },
    {
        "ministry": "KEMENTERIAN PERDAGANGAN DALAM NEGERI DAN HAL EHWAL PENGGUNA (KPDNHEP)",
        "department": "PERBADANAN HARTA INTELEK MALAYSIA (MYIPO)"
    },
    {
        "ministry": "KEMENTERIAN PERDAGANGAN DALAM NEGERI DAN HAL EHWAL PENGGUNA (KPDNHEP)",
        "department": "SURUHANJAYA PERSAINGAN MALAYSIA (MYCC)"
    },
    {
        "ministry": "KEMENTERIAN PERDAGANGAN DALAM NEGERI DAN HAL EHWAL PENGGUNA (KPDNHEP)",
        "department": "SURUHANJAYA SYARIKAT MALAYSIA (SSM)"
    },
    {
        "ministry": "KEMENTERIAN PERPADUAN NEGARA",
        "department": "INSTITUT KAJIAN & LATIHAN INTEGRASI NASIONAL (IKLIN)"
    },
    {
        "ministry": "KEMENTERIAN PERPADUAN NEGARA",
        "department": "KEMENTERIAN PERPADUAN NEGARA"
    },
    {
        "ministry": "KEMENTERIAN PERTAHANAN",
        "department": "JABATAN HAL EHWAL VETERAN ATM"
    },
    {
        "ministry": "KEMENTERIAN PERTAHANAN",
        "department": "KEMENTERIAN PERTAHANAN"
    },
    {
        "ministry": "KEMENTERIAN PERTAHANAN",
        "department": "MARKAS ANGKATAN TENTERA MALAYSIA"
    },
    {
        "ministry": "KEMENTERIAN PERTAHANAN",
        "department": "TENTERA DARAT MALAYSIA"
    },
    {
        "ministry": "KEMENTERIAN PERTAHANAN",
        "department": "TENTERA LAUT DIRAJA MALAYSIA"
    },
    {
        "ministry": "KEMENTERIAN PERTAHANAN",
        "department": "TENTERA UDARA DIRAJA MALAYSIA"
    },
    {
        "ministry": "KEMENTERIAN PERTANIAN DAN INDUSTRI ASAS TANI",
        "department": "INSTITUT PENYELIDIKAN DAN KEMAJUAN PERTANIAN MALAYSIA (MARDI)"
    },
    {
        "ministry": "KEMENTERIAN PERTANIAN DAN INDUSTRI ASAS TANI",
        "department": "JABATAN PERIKANAN MALAYSIA"
    },
    {
        "ministry": "KEMENTERIAN PERTANIAN DAN INDUSTRI ASAS TANI",
        "department": "JABATAN PERKHIDMATAN KUARANTIN DAN PEMERIKSAAN MALAYSIA (MAQIS)"
    },
    {
        "ministry": "KEMENTERIAN PERTANIAN DAN INDUSTRI ASAS TANI",
        "department": "JABATAN PERKHIDMATAN VETERINAR (DVS)"
    },
    {
        "ministry": "KEMENTERIAN PERTANIAN DAN INDUSTRI ASAS TANI",
        "department": "JABATAN PERTANIAN MALAYSIA"
    },
    {
        "ministry": "KEMENTERIAN PERTANIAN DAN INDUSTRI ASAS TANI",
        "department": "KEMENTERIAN PERTANIAN DAN INDUSTRI ASAS TANI"
    },
    {
        "ministry": "KEMENTERIAN PERTANIAN DAN INDUSTRI ASAS TANI",
        "department": "LEMBAGA KEMAJUAN IKAN MALAYSIA (LKIM)"
    },
    {
        "ministry": "KEMENTERIAN PERTANIAN DAN INDUSTRI ASAS TANI",
        "department": "LEMBAGA KEMAJUAN PERTANIAN KEMUBU (KADA)"
    },
    {
        "ministry": "KEMENTERIAN PERTANIAN DAN INDUSTRI ASAS TANI",
        "department": "LEMBAGA KEMAJUAN PERTANIAN MUDA (MADA)"
    },
    {
        "ministry": "KEMENTERIAN PERTANIAN DAN INDUSTRI ASAS TANI",
        "department": "LEMBAGA PEMASARAN PERTANIAN PERSEKUTUAN (FAMA)"
    },
    {
        "ministry": "KEMENTERIAN PERTANIAN DAN INDUSTRI ASAS TANI",
        "department": "LEMBAGA PERINDUSTRIAN NANAS MALAYSIA (LPNM)"
    },
    {
        "ministry": "KEMENTERIAN PERTANIAN DAN INDUSTRI ASAS TANI",
        "department": "LEMBAGA PERTUBUHAN PELADANG (LPP)"
    },
    {
        "ministry": "KEMENTERIAN PERUMAHAN DAN KERAJAAN TEMPATAN",
        "department": "JABATAN KERAJAAN TEMPATAN"
    },
    {
        "ministry": "KEMENTERIAN PERUMAHAN DAN KERAJAAN TEMPATAN",
        "department": "JABATAN PERUMAHAN NEGARA"
    },
    {
        "ministry": "KEMENTERIAN PERUMAHAN DAN KERAJAAN TEMPATAN",
        "department": "KEMENTERIAN PERUMAHAN DAN KERAJAAN TEMPATAN"
    },
    {
        "ministry": "KEMENTERIAN PERUMAHAN DAN KERAJAAN TEMPATAN",
        "department": "PERBADANAN PENGURUSAN SISA PEPEJAL DAN PEMBERSIHAN AWAM (SWCORP) "
    },
    {
        "ministry": "KEMENTERIAN SUMBER MANUSIA",
        "department": "INSTITUT KESELAMATAN DAN KESIHATAAN PEKERJAAN NEGARA (NIOSH)"
    },
    {
        "ministry": "KEMENTERIAN SUMBER MANUSIA",
        "department": "INSTITUT MAKLUMAT & ANALISIS PASARAN BURUH (ILMIA)"
    },
    {
        "ministry": "KEMENTERIAN SUMBER MANUSIA",
        "department": "JABATAN HAL EHWAL KESATUAN SEKERJA"
    },
    {
        "ministry": "KEMENTERIAN SUMBER MANUSIA",
        "department": "JABATAN KESELAMATAN DAN KESIHATAN PEKERJAAN MALAYSIA"
    },
    {
        "ministry": "KEMENTERIAN SUMBER MANUSIA",
        "department": "JABATAN PERHUBUNGAN PERUSAHAAN"
    },
    {
        "ministry": "KEMENTERIAN SUMBER MANUSIA",
        "department": "JABATAN TENAGA KERJA SABAH"
    },
    {
        "ministry": "KEMENTERIAN SUMBER MANUSIA",
        "department": "JABATAN TENAGA KERJA SARAWAK"
    },
    {
        "ministry": "KEMENTERIAN SUMBER MANUSIA",
        "department": "JABATAN TENAGA KERJA SEMENANJUNG MALAYSIA"
    },
    {
        "ministry": "KEMENTERIAN SUMBER MANUSIA",
        "department": "JABATAN TENAGA MANUSIA"
    },
    {
        "ministry": "KEMENTERIAN SUMBER MANUSIA",
        "department": "KEMENTERIAN SUMBER MANUSIA"
    },
    {
        "ministry": "KEMENTERIAN SUMBER MANUSIA",
        "department": "MAHKAMAH PERUSAHAAN MALAYSIA"
    },
    {
        "ministry": "KEMENTERIAN SUMBER MANUSIA",
        "department": "PEMBANGUNAN SUMBER MANUSIA BERHAD (PSMB)"
    },
    {
        "ministry": "KEMENTERIAN SUMBER MANUSIA",
        "department": "PERTUBUHAN KESELAMATAN SOSIAL (PERKESO)"
    },
    {
        "ministry": "KEMENTERIAN TENAGA DAN SUMBER ASLI",
        "department": "INSTITUT PENYELIDIKAN HIDRAULIK KEBANGSAAN MALAYSIA (NAHRIM)"
    },
    {
        "ministry": "KEMENTERIAN TENAGA DAN SUMBER ASLI",
        "department": "INSTITUT PENYELIDIKAN PERHUTANAN MALAYSIA (FRIM)"
    },
    {
        "ministry": "KEMENTERIAN TENAGA DAN SUMBER ASLI",
        "department": "INSTITUT TANAH DAN UKUR NEGARA (INSTUN)"
    },
    {
        "ministry": "KEMENTERIAN TENAGA DAN SUMBER ASLI",
        "department": "JABATAN BIOKESELAMATAN MALAYSIA"
    },
    {
        "ministry": "KEMENTERIAN TENAGA DAN SUMBER ASLI",
        "department": "JABATAN KETUA PENGARAH TANAH DAN GALIAN PERSEKUTUAN (JKPTG)"
    },
    {
        "ministry": "KEMENTERIAN TENAGA DAN SUMBER ASLI",
        "department": "JABATAN MINERAL DAN GEOSAINS MALAYSIA (JMG)"
    },
    {
        "ministry": "KEMENTERIAN TENAGA DAN SUMBER ASLI",
        "department": "JABATAN PENGAIRAN DAN SALIRAN (JPS)"
    },
    {
        "ministry": "KEMENTERIAN TENAGA DAN SUMBER ASLI",
        "department": "JABATAN PERHUTANAN SEMENANJUNG MALAYSIA"
    },
    {
        "ministry": "KEMENTERIAN TENAGA DAN SUMBER ASLI",
        "department": "JABATAN PERLINDUNGAN HIDUPAN LIAR DAN TAMAN NEGARA (PERHILITAN)"
    },
    {
        "ministry": "KEMENTERIAN TENAGA DAN SUMBER ASLI",
        "department": "JABATAN UKUR DAN PEMETAAN MALAYSIA (JUPEM)"
    },
    {
        "ministry": "KEMENTERIAN TENAGA DAN SUMBER ASLI",
        "department": "KEMENTERIAN TENAGA DAN SUMBER ASLI"
    },
    {
        "ministry": "KEMENTERIAN TENAGA DAN SUMBER ASLI",
        "department": "LEMBAGA AHLI GEOLOGI"
    },
    {
        "ministry": "KEMENTERIAN TENAGA DAN SUMBER ASLI",
        "department": "LEMBAGA JURUUKUR TANAH"
    },
    {
        "ministry": "KEMENTERIAN TENAGA DAN SUMBER ASLI",
        "department": "PIHAK BERKUASA PEMBANGUNAN TENAGA LESTARI MALAYSIA (SEDA)"
    },
    {
        "ministry": "KEMENTERIAN TENAGA DAN SUMBER ASLI",
        "department": "SURUHANJAYA TENAGA (EC)"
    },
    {
        "ministry": "KEMENTERIAN TENAGA DAN SUMBER ASLI",
        "department": "YAYASAN HIJAU MALAYSIA"
    },
    {
        "ministry": "KEMENTERIAN TENAGA, SAINS, TEKNOLOGI, ALAM SEKITAR DAN PERUBAHAN IKLIM (MESTECC)",
        "department": "AGENSI ANGKASA MALAYSIA (MYSA)"
    },
    {
        "ministry": "KEMENTERIAN TENAGA, SAINS, TEKNOLOGI, ALAM SEKITAR DAN PERUBAHAN IKLIM (MESTECC)",
        "department": "AGENSI NUKLEAR MALAYSIA (NUKLEAR MALAYSIA)"
    },
    {
        "ministry": "KEMENTERIAN TENAGA, SAINS, TEKNOLOGI, ALAM SEKITAR DAN PERUBAHAN IKLIM (MESTECC)",
        "department": "JABATAN ALAM SEKITAR (JAS)"
    },
    {
        "ministry": "KEMENTERIAN TENAGA, SAINS, TEKNOLOGI, ALAM SEKITAR DAN PERUBAHAN IKLIM (MESTECC)",
        "department": "JABATAN KIMIA MALAYSIA"
    },
    {
        "ministry": "KEMENTERIAN TENAGA, SAINS, TEKNOLOGI, ALAM SEKITAR DAN PERUBAHAN IKLIM (MESTECC)",
        "department": "JABATAN METEOROLOGI MALAYSIA"
    },
    {
        "ministry": "KEMENTERIAN TENAGA, SAINS, TEKNOLOGI, ALAM SEKITAR DAN PERUBAHAN IKLIM (MESTECC)",
        "department": "KEMENTERIAN SAINS, TEKNOLOGI & INOVASI (MOSTI)"
    },
    {
        "ministry": "KEMENTERIAN TENAGA, SAINS, TEKNOLOGI, ALAM SEKITAR DAN PERUBAHAN IKLIM (MESTECC)",
        "department": "LEMBAGA PERLESENAN TENAGA ATOM (LPTA)"
    },
    {
        "ministry": "KEMENTERIAN WILAYAH PERSEKUTUAN",
        "department": "DEWAN BANDARAYA KUALA LUMPUR (DBKL)"
    },
    {
        "ministry": "KEMENTERIAN WILAYAH PERSEKUTUAN",
        "department": "JABATAN LANDSKAP NEGARA"
    },
    {
        "ministry": "KEMENTERIAN WILAYAH PERSEKUTUAN",
        "department": "JABATAN PERANCANGAN BANDAR DAN DESA SEMENANJUNG MALAYSIA"
    },
    {
        "ministry": "KEMENTERIAN WILAYAH PERSEKUTUAN",
        "department": "KEMENTERIAN WILAYAH PERSEKUTUAN"
    },
    {
        "ministry": "KEMENTERIAN WILAYAH PERSEKUTUAN",
        "department": "MAJLIS SUKAN WILAYAH PERSEKUTUAN"
    },
    {
        "ministry": "KEMENTERIAN WILAYAH PERSEKUTUAN",
        "department": "PEJABAT TANAH DAN GALIAN WILAYAH PERSEKUTUAN(PTG WP)"
    },
    {
        "ministry": "KEMENTERIAN WILAYAH PERSEKUTUAN",
        "department": "PERBADANAN LABUAN"
    },
    {
        "ministry": "KEMENTERIAN WILAYAH PERSEKUTUAN",
        "department": "PERBADANAN PEMBANGUNAN KAMPONG BHARU (PKB)"
    },
    {
        "ministry": "KEMENTERIAN WILAYAH PERSEKUTUAN",
        "department": "PERBADANAN PUTRAJAYA"
    }
]